alibabacloud_nbftestpop20210802_16102392/__init__.py
alibabacloud_nbftestpop20210802_16102392/client.py
alibabacloud_nbftestpop20210802_16102392/models.py
alibabacloud_nbftestpop20210802_16102392-6.0.0.dist-info/LICENSE
alibabacloud_nbftestpop20210802_16102392-6.0.0.dist-info/METADATA
alibabacloud_nbftestpop20210802_16102392-6.0.0.dist-info/WHEEL
alibabacloud_nbftestpop20210802_16102392-6.0.0.dist-info/top_level.txt
alibabacloud_nbftestpop20210802_16102392-6.0.0.dist-info/RECORD
